ColorChalks/ColorChalks.py
ColorChalks/__init__.py
ColorChalks-1.0.3.dist-info/LICENSE
ColorChalks-1.0.3.dist-info/METADATA
ColorChalks-1.0.3.dist-info/WHEEL
ColorChalks-1.0.3.dist-info/top_level.txt
ColorChalks-1.0.3.dist-info/RECORD
